tomo/__init__.py
tomo/core.py
tomo/etc.py
tomo/projection.py
tomo/version.py
tomo-0.0.1.dist-info/METADATA
tomo-0.0.1.dist-info/RECORD
tomo-0.0.1.dist-info/WHEEL
tomo-0.0.1.dist-info/top_level.txt
